request_normalizer/RequestRepository.py
request_normalizer/__init__.py
request_normalizer/middleware.py
bear_django_request_normalizer-0.2.0.dist-info/METADATA
bear_django_request_normalizer-0.2.0.dist-info/WHEEL
bear_django_request_normalizer-0.2.0.dist-info/top_level.txt
bear_django_request_normalizer-0.2.0.dist-info/RECORD
