Metadata-Version: 2.4
Name: bear-django-request-normalizer
Version: 0.2.0
Summary: A Django middleware to clean and normalize incoming request data (GET, POST, JSON).
Author-email: Bohdan Riabunets <bearablyk@gmail.com>
License-Expression: MIT
Project-URL: Homepage, https://github.com/bearablyk/django-request-normalizer
Project-URL: Issues, https://github.com/bearablyk/django-request-normalizer/issues
Classifier: Programming Language :: Python :: 3
Classifier: Operating System :: OS Independent
Classifier: Framework :: Django
Classifier: Topic :: Internet :: WWW/HTTP :: WSGI :: Middleware
Requires-Python: >=3.8
Requires-Dist: Django>=3.2
